circuitpython_vl53lxcx-0.0.5.dist-info/licenses/LICENSE
vl53lxcx/__init__.py
vl53lxcx/vl53l5cx_fw.bin
vl53lxcx/vl53l8cx_fw.bin
vl53lxcx/vl_fw_config.bin
circuitpython_vl53lxcx-0.0.5.dist-info/METADATA
circuitpython_vl53lxcx-0.0.5.dist-info/WHEEL
circuitpython_vl53lxcx-0.0.5.dist-info/top_level.txt
circuitpython_vl53lxcx-0.0.5.dist-info/RECORD
