Metadata-Version: 2.4
Name: circuitpython-vl53lxcx
Version: 0.0.5
Summary: CircuitPython driver for VL53L5CX and VL53L8CX ToF sensors
Author-email: senseBox <info@sensebox.de>
License: MIT
Project-URL: Homepage, https://github.com/sensebox/CircuitPython_VL53LxCX
Keywords: adafruit,blinka,circuitpython,micropython,vl53lxcx,VL53L5CX,VL53L8CX
Classifier: Intended Audience :: Developers
Classifier: Topic :: Software Development :: Libraries
Classifier: Topic :: Software Development :: Embedded Systems
Classifier: Topic :: System :: Hardware
Classifier: License :: OSI Approved :: MIT License
Classifier: Programming Language :: Python :: 3
License-File: LICENSE
Requires-Dist: Adafruit-Blinka
Requires-Dist: adafruit-circuitpython-busdevice
Requires-Dist: adafruit-circuitpython-register
Provides-Extra: optional
Dynamic: license-file
